{
  "schemaVersion": 1,
  "id": "duel_hall_of_mirrors",
  "type": "duel",
  "name": "The Duel in the Hall",
  "locationId": "the_hall_of_mirrors",
  "setup": "You have been challenged in the Hall of Mirrors, which means you have been challenged by someone who may not be standing where you can see them, using a face that may not be theirs.",
  "lethal": false,
  "opponent": {
    "name": "a Veilwright",
    "health": 4,
    "threat": 40,
    "yieldAt": 1,
    "fleeDifficulty": 15,
    "spectrum": {
      "falsehood_truth": -0.6
    },
    "tacticTags": [
      "is-not-where-you-thought",
      "wears-another-face",
      "lets-you-hit-the-wrong-one",
      "admits-nothing"
    ]
  }
}
