{
  "schemaVersion": 1,
  "id": "the_grand_lattice",
  "name": "The Grand Lattice",
  "regionId": "the_lattice_cities",
  "communityId": "lattice.grand",
  "axisVector": [
    0.4,
    0.0,
    0.0,
    0.0,
    0.0,
    0.0,
    1.0,
    0.0,
    0.0,
    0.0,
    0.3,
    0.0
  ],
  "spectrum": {
    "chaos_order": 1.0,
    "body_mind": 0.3,
    "emotional_logical": 0.4
  },
  "tags": [
    "lattice",
    "order",
    "locus",
    "cult",
    "dangerous",
    "sacred"
  ],
  "connections": [
    "tier_seven"
  ],
  "descriptionSeed": "The inner ring, where order stopped being a method and became a faith. Here nothing is unplanned and nothing is free, and the second clause is not a cost of the first — it is the POINT. Freedom, in the Grand Lattice's mature doctrine, is a defect: the residue of an unsolved optimization. They are not cruel. They are finishing the work. The other tiers do not come here and do not discuss why.",
  "loreRefs": [
    "the_twelve_reaches",
    "traditions",
    "the_coordinate_world"
  ],
  "encounterFlavor": "The inner-ring devoted, who are serene and have solved you; a plan that includes you and that you did not consent to; a citizen who has been optimized past personhood and is grateful.",
  "dangerLevel": 5,
  "questSeeds": [
    "The inner ring has produced a plan for the entire world and it is elegant and it is coming",
    "Someone you know has been scheduled, and the schedule is correct, and it ends them"
  ],
  "map": {
    "x": 480,
    "y": 150
  },
  "poleIntensity": {
    "order": 1.0,
    "mind": 0.3,
    "logical": 0.4
  },
  "substrateSource": {
    "kind": "pool",
    "delta": 0.2,
    "radius": 165,
    "reason": "The Lattice was built INTO the substrate rather than on top of it; the city and the pool are the same structure."
  }
}
